Workbook
Name Running_M: 'India Rollout'!$B$14
Name Rent_Method: Profitability!$B$19
Name Rent_Sold: Profitability!$B$20
Name ST_Target: Inputs!$B$45
Name COD_Share: Inputs!$B$5
Name Maint_P: Profitability!$B$57
Name Net_Sold_High: 'Unit Economics'!$D$23
Name OneTime_Hubs: 'India Rollout'!$B$12
Name Gateway: Inputs!$B$27
Name Y_ST: 'India Rollout'!$B$18:$E$18
Name Eligible: Inputs!$B$10
Name RTO_Prepaid: Inputs!$B$7
Name Prof2: Profitability!$C$34
Name Hubs: Inputs!$B$8
Name RTO_Rate: 'India Rollout'!$B$3
Name Y_NetBase: 'India Rollout'!$B$21:$E$21
Name Remote_Uplift: 'Unit Economics'!$B$41
Name TierB_Transfer: 'Unit Economics'!$C$39
Name Save_Unsold: 'Unit Economics'!$E$24
Name C_Training: Inputs!$B$53
Name Route_Sourced: 'Unit Economics'!$B$32
Name ST_M1: Profitability!$B$22
Name Rent_Parcel: Profitability!$B$18
Name AOV: Inputs!$B$39
Name Route_High: Inputs!$B$26
Name N_FMCart: Inputs!$B$15
Name Routed_D_P: Profitability!$B$55
Name LM_Remote: Inputs!$B$31
Name YP_Base: Profitability!$B$104:$E$104
Name Y_Share: 'India Rollout'!$B$20:$E$20
Name Y_Saved: 'India Rollout'!$B$19:$E$19
Name Days_Sold: Inputs!$B$35
Name Prof1: Profitability!$B$34
Name RTO_Cost_Year: 'India Rollout'!$B$24
Name N_FMSC: Inputs!$B$16
Name Orders: Inputs!$B$4
Name RTO_Day: 'India Rollout'!$B$4
Name Routed_Hub: Profitability!$B$17
Name OneTime_P: Profitability!$B$58
Name Shelf: Inputs!$B$9
Name Leg_Other: 'Unit Economics'!$B$7
Name C_Scanner: Inputs!$B$51
Name Save_Sold_High: 'Unit Economics'!$D$24
Name Payback_High: 'India Rollout'!$C$23
Name Rent_Hub: Profitability!$B$16
Name N_LMSC: Inputs!$B$18
Name OneTime_Central: 'India Rollout'!$B$11
Name Other_Avoid: Inputs!$B$22
Name Rev_Sale: Profitability!$B$12
Name N_LMDC: Inputs!$B$20
Name C_Maint: Inputs!$B$54
Name N_FMHub: Inputs!$B$14
Name Leg_Attempt: 'Unit Economics'!$B$5
Name Cap_Day: 'India Rollout'!$B$6
Name Rent_Unsold: Profitability!$B$21
Name Net_Today: 'Unit Economics'!$B$23
Name RTO_Avoid_Sale: Profitability!$B$125
Name ST_Start: Inputs!$B$44
Name C_Support: Inputs!$B$55
Name C_HubMonthly: Inputs!$B$56

Sheet Summary
A1: Hypersale — financial summary
A2: Per parcel | D2: India-wide (all 2,700 hubs)
B3: ₹35 base | C3: ₹45 high | E3: ₹35 base | F3: ₹45 high
A4: Today: cost of one RTO | B4: =-Net_Today -> 120 | C4: =-Net_Today -> 120 | D4: Year 1 net profit (after setup) | E4: {=INDEX(Y_NetBase,1)} -> 410.94251 | F4: {=INDEX(Y_NetHigh,1)} -> 376.66999
A5: Saving when a parcel sells | B5: =Save_Sold_Base -> 127.72058 | C5: =Save_Sold_High -> 117.72058 | D5: Year 2 net profit | E5: {=INDEX(Y_NetBase,2)} -> 669.90238 | F5: {=INDEX(Y_NetHigh,2)} -> 615.78787
A6: Saving when it doesn't sell | B6: =Save_Unsold -> -2.2764228 | C6: =Save_Unsold -> -2.2764228 | D6: 3-year net profit | E6: {=INDEX(Y_NetBase,4)} -> 1750.7473 | F6: {=INDEX(Y_NetHigh,4)} -> 1608.2457
A7: Saving per parcel routed (steady state) | B7: =ST_Target*Save_Sold_Base+(1-ST_Target)*Save_Unsold -> 46.472452 | C7: =ST_Target*Save_Sold_High+(1-ST_Target)*Save_Unsold -> 42.722452 | D7: Payback month | E7: =Payback_Base -> 1 | F7: =Payback_High -> 1
A8: Furthest profitable radius | B8: =IF('Unit Economics'!D40>0,"Another city",IF('Unit Economics'!D39>0,"Nearby hub","Same hub only")) -> Another city | C8: =IF('Unit Economics'!E40>0,"Another city",IF(ROUND('Unit Economics'!E39,2)>0,"Nearby hub","Same hub only")) -> Another city | D8: One-time setup cost | E8: =OneTime/10^7 -> 1.02 | F8: =OneTime/10^7 -> 1.02
A10: RTO impact
B11: Year 1 | C11: Year 2
A12: RTO parcels saved from the reverse trip | B12: {=INDEX(Y_Saved,1)} -> 342.72522 | C12: {=INDEX(Y_Saved,2)} -> 541.14509
A13: Share of all RTO parcels saved | B13: {=INDEX(Y_Share,1)} -> 0.13150885 | C13: {=INDEX(Y_Share,2)} -> 0.20764556
A14: Parcels routed into Hypersale per day | B14: =Routed_Day -> 395357.14 | C14: =IF(Elig_Day>Cap_Day,"limited by shelf space","limited by eligible parcels") -> limited by shelf space
A15: Today's total Valmo RTO cost per year | B15: =RTO_Cost_Year -> 3127.32
A17: Key assumptions
A18: Assumption | B18: Value | D18: Type
A19: Sell-through: month 1 → steady state | B19: =TEXT(ST_Start,"0%")&" → "&TEXT(ST_Target,"0.0%")&" over "&Ramp&" months" -> 10% → 37.5% over 12 months | D19: Assumption; 37.5% = Zomato proxy (ceiling)
A20: Routing + repack + delivery per sale | B20: ="₹"&Route_Base&" base / ₹"&Route_High&" high" -> ₹35 base / ₹45 high | D20: Assumption anchored to ₹31.7 sourced
A21: Fees per sale (express + seller) | B21: ="₹"&TEXT(AOV*Fee_Express,"0")&" + ₹"&TEXT(AOV*Fee_Seller,"0") -> ₹15 + ₹30 | D21: Assumption
A22: Eligible share of RTO parcels | B22: =Eligible -> 0.9 | D22: Assumption
A23: RTO parcels routed limited by | B23: ="Shelf: "&TEXT(Shelf,"0")&" per hub per week" -> Shelf: 1025 per hub per week | D23: Design decision
A24: App build + cloud setup | B24: =OneTime_Central/10^7 -> 1.02 | D24: Published source (top of range)

Sheet Inputs
A1: Input Costs
A2: Assumption | B2: Value | C2: Unit | D2: Source / note
A3: A. Network & volume
A4: Valmo orders per day | B4: 4200000 | C4: orders | D4: Team field research: ~42 lakh Valmo orders/day
A5: COD share of orders | B5: 0.8 | C5: % | D5: Case data pack
A6: RTO rate — COD orders | B6: 0.2 | C6: % | D6: Case data pack
A7: RTO rate — prepaid orders | B7: 0.05 | C7: % | D7: Case data pack
A8: Valmo last-mile hubs | B8: 2700 | C8: hubs | D8: Team field research
A9: Hold-shelf capacity per hub | B9: =0.65*500+0.35*2000 -> 1025 | C9: parcels/week | D9: Shelf holds one week of RTO pieces (~500/hub)
A10: Share of RTO parcels eligible for Hypersale | B10: 0.9 | C10: % | D10: Rest excluded: opened/damaged, large, perishable (cf. Ozon's exclusions)
A12: B. Today's cost of one RTO (₹ per order)
A13: Total cost of one RTO | B13: 120 | C13: ₹/order | D13: Case data pack: ₹120 per RTO shipment (total)
A14: Node cost — First-mile hub | B14: 4 | C14: ₹/order | D14: Case data pack node split
A15: Node cost — First-mile carting | B15: 2 | C15: ₹/order | D15: Case data pack node split
A16: Node cost — Source sort centre (FMSC) | B16: 5 | C16: ₹/order | D16: Case data pack node split
A17: Node cost — National line haul | B17: 8 | C17: ₹/order | D17: Case data pack node split
A18: Node cost — Destination sort centre (LMSC) | B18: 5 | C18: ₹/order | D18: Case data pack node split
A19: Node cost — Regional line haul | B19: 5 | C19: ₹/order | D19: Case data pack node split
A20: Node cost — Last-mile delivery (LMDC) | B20: 14 | C20: ₹/order | D20: Rest ₹7 Accounted later
A21: Reverse trip back to the seller | B21: 29 | C21: ₹/order | D21: Retraces the forward path to the last-mile hub (₹29); not given separately in the pack
A22: Share of 'other RTO costs' avoided when the item is resold | B22: 0.3 | C22: % | D22: atleast ₹24 is saved
A24: C. Hypersale cost per sale
A25: Routing + repack + delivery — BASE case | B25: 35 | C25: ₹/sale | D25: Anchored to the sourced breakup on 'Unit Economics' (₹31.7) + ~4 min hub labour
A26: Routing + repack + delivery — HIGH case | B26: 45 | C26: ₹/sale | D26: ₹31.7 sourced + ~17 min hub labour, re-sort and support
A27: Payment gateway fee (Hypersale is prepaid only) | B27: 0.0236 | C27: % of payment | D27: Razorpay standard: 2% + 18% GST
A28: New tamper-proof courier bag | B28: 1.5 | C28: ₹/sale | D28: IndiaMART: LDPE security envelope, ₹3/piece
A29: New shipping label | B29: 1 | C29: ₹/sale | D29: IndiaMART label listings: ₹0.25–1/piece (top used)
A30: Hub staff wage | B30: 15000 | C30: ₹/month | D30: 500 x 7 x (30/7) with ₹7 commission to hub manager
A31: Last-mile cost when the buyer is at another hub | B31: 25 | C31: ₹/sale | D31: Team assumption for extended-radius deliveries (vs ₹21 local)
A32: Share of sales delivered from another hub (Tier B) | B32: 0.25 | C32: % | D32: Needs hub data; see 'Scenarios' for 10–65%
A33: Listing / QC cost per held item (paid even if unsold) | B33: 0 | C33: ₹/item | D33: Set to 0 if already inside the ₹35/₹45
A34: Holding cost per item per day | B34: =((10000/30)/(Shelf/7)) -> 2.2764228 | C34: ₹/item/day | D34: Rent ₹10,000/month ÷ 30 days ÷ parcels sitting on the shelf at one time (≈ one week's intake = Shelf). Rent counted here only.
A35: Average days held before a sale | B35: 3 | C35: days | D35: Needs pilot data
A36: Maximum hold window | B36: 7 | C36: days | D36: Unsold items go back to the seller after 7 days
A38: D. Hypersale revenue
A39: Average order value | B39: 270 | C39: ₹/order | D39: Team field research
A40: Customer express fee | B40: 0.055555556 | C40: % of AOV | D40: Equals ₹15; team's own ₹10–15 for 1-day delivery. Ref: Amazon ₹5, Flipkart ₹3 platform fees
A41: Seller protection fee | B41: 0.1111 | C41: % of AOV | D41: Equals ₹20; no benchmark — sellers' alternative is a ₹35–45 reship (Shiprocket)
A43: E. Demand (sell-through)
A44: Sell-through in month 1 | B44: 0.1 | C44: % | D44: Team assumption
A45: Sell-through at steady state | B45: 0.375 | C45: % | D45: Ceiling proxy: Zomato Food Rescue ~1.5 of ~4 lakh cancelled orders/month (Storyboard18, Mar 2025)
A46: Months to reach steady state | B46: 12 | C46: months | D46: Linear climb month on month
A48: F. Setup & running costs
A49: App/site build (Hypersale tab, hold logic, hub screens) | B49: 10000000 | C49: ₹ one-time | D49: IndianWeb 2026 guide: enterprise build ₹20 L–₹1 Cr+ (top used)
A50: Cloud infrastructure setup | B50: 200000 | C50: ₹ one-time | D50: IRPR Agency 2026: under ₹2 lakh
A51: Barcode scanner per hub | B51: 0 | C51: ₹ per hub | D51: Techjockey: TVS BSC 101
A52: Storage racks per hub | B52: 0 | C52: ₹ per hub | D52: Rack spec found, no reliable price
A53: Hub training per hub | B53: 0 | C53: ₹ per hub | D53: No source yet
A54: App maintenance & support | B54: 600000 | C54: ₹/month | D54: IndianWeb 2026 guide: ₹1.5–6 L/month (top used)
A55: Customer support for Hypersale orders | B55: 0 | C55: ₹/month | D55: No incremental value
A56: Per-hub running cost (space payout, staff time, consumables) | B56: 0 | C56: ₹/hub/month | D56: Set to 0: the ₹10,000 rent is already in the holding cost per item (row 38). Enter only costs other than rent here.
A57: Label printer | B57: 0 | C57: ₹ per hub | D57: Every hub already has one (team field data)

Sheet Profitability
A1: Hypersale profitability — the channel pays for itself on fees alone
A2: A. What this view counts, and what it leaves out
A3: Counted as revenue | B3: Customer express fee + seller protection fee, on every Hypersale sale
A4: Counted as cost | B4: Routing + repack + delivery to the new buyer, and shelf rent
A5: NOT counted (upside) | B5: The ₹29 reverse trip the sale avoids, and any share of the ₹62 other RTO cost — shown as a memo line only
A6: NOT counted (removed) | B6: The ₹6.5 average remote-hub transfer cost
A7: B. Inputs for this view
A8: Input | B8: Value | C8: Unit
A9: Average order value | B9: =AOV -> 270 | C9: ₹/order
A10: Customer express fee | B10: =Fee_Express -> 0.055555556 | C10: % of AOV
A11: Seller protection fee | B11: =Fee_Seller -> 0.1111 | C11: % of AOV
A12: Revenue per Hypersale sale | B12: =AOV_P*FeeE_P+AOV_P*FeeS_P -> 44.997 | C12: ₹/sale
A13: Routing + repack + delivery — case 1 | B13: =Route_Base -> 35 | C13: ₹/sale
A14: Routing + repack + delivery — case 2 | B14: 40 | C14: ₹/sale
A15: Routing + repack + delivery — case 3 | B15: =Route_High -> 45 | C15: ₹/sale
A16: Shelf rent per hub | B16: 10000 | C16: ₹/month
A17: Parcels routed per hub | B17: =Shelf*30/7 -> 4392.8571 | C17: parcels/month
A18: Shelf rent per parcel routed | B18: =Rent_Hub/Routed_Hub -> 2.2764228 | C18: ₹/parcel
A19: Rent method: 1 = once per parcel routed, 2 = per day on the shelf | B19: 1 | C19: 1 or 2
A20: Rent charged to a parcel that sells | B20: =IF(Rent_Method=1,Rent_Parcel,Rent_Parcel*Days_Sold) -> 2.2764228 | C20: ₹/sale
A21: Rent charged to a parcel that does not sell | B21: =IF(Rent_Method=1,Rent_Parcel,Rent_Parcel*Hold_Max) -> 2.2764228 | C21: ₹/parcel
A22: Sell-through, month 1 | B22: 0.05 | C22: %
A23: Sell-through, end of year 1 (month 12) | B23: 0.2 | C23: %
A24: Sell-through, end of year 3 (month 36) | B24: 0.375 | C24: %
A26: C. Profit on one Hypersale sale
A27: ₹ per sale | B27: ₹35 case | C27: ₹40 case | D27: ₹45 case
A28: Customer express fee | B28: =AOV_P*FeeE_P -> 15 | C28: =AOV_P*FeeE_P -> 15 | D28: =AOV_P*FeeE_P -> 15
A29: Seller protection fee | B29: =AOV_P*FeeS_P -> 29.997 | C29: =AOV_P*FeeS_P -> 29.997 | D29: =AOV_P*FeeS_P -> 29.997
A30: Revenue per sale | B30: =SUM(B28:B29) -> 44.997 | C30: =SUM(C28:C29) -> 44.997 | D30: =SUM(D28:D29) -> 44.997
A31: Routing + repack + delivery to the new buyer | B31: -35 | C31: -45 | D31: -55
A32: Shelf rent | B32: =-Rent_Sold -> -2.2764228 | C32: =-Rent_Sold -> -2.2764228 | D32: =-Rent_Sold -> -2.2764228
A33: Cost per sale | B33: =SUM(B31:B32) -> -37.276423 | C33: =SUM(C31:C32) -> -47.276423 | D33: =SUM(D31:D32) -> -57.276423
A34: PROFIT per sale | B34: =B30+B33 -> 7.7205772 | C34: =C30+C33 -> -2.2794228 | D34: =D30+D33 -> -12.279423
A35: Margin on the sale | B35: =B34/B30 -> 0.17157982 | C35: =C34/C30 -> -0.050657216 | D35: =D34/D30 -> -0.27289425
A37: D. Profit on one parcel put on the shelf (sold and unsold together)
A38: Sell-through | B38: ₹35 case | C38: ₹40 case | D38: ₹45 case
A39: 0.05 | B39: =$A39*Prof1-(1-$A39)*Rent_Unsold -> -1.7765728 | C39: =$A39*Prof2-(1-$A39)*Rent_Unsold -> -2.2765728 | D39: =$A39*Prof3-(1-$A39)*Rent_Unsold -> -2.7765728
A40: 0.1 | B40: =$A40*Prof1-(1-$A40)*Rent_Unsold -> -1.2767228 | C40: =$A40*Prof2-(1-$A40)*Rent_Unsold -> -2.2767228 | D40: =$A40*Prof3-(1-$A40)*Rent_Unsold -> -3.2767228
A41: 0.2 | B41: =$A41*Prof1-(1-$A41)*Rent_Unsold -> -0.27702276 | C41: =$A41*Prof2-(1-$A41)*Rent_Unsold -> -2.2770228 | D41: =$A41*Prof3-(1-$A41)*Rent_Unsold -> -4.2770228
A42: 0.25 | B42: =$A42*Prof1-(1-$A42)*Rent_Unsold -> 0.22282724 | C42: =$A42*Prof2-(1-$A42)*Rent_Unsold -> -2.2771728 | D42: =$A42*Prof3-(1-$A42)*Rent_Unsold -> -4.7771728
A43: 0.3 | B43: =$A43*Prof1-(1-$A43)*Rent_Unsold -> 0.72267724 | C43: =$A43*Prof2-(1-$A43)*Rent_Unsold -> -2.2773228 | D43: =$A43*Prof3-(1-$A43)*Rent_Unsold -> -5.2773228
A44: 0.375 | B44: =$A44*Prof1-(1-$A44)*Rent_Unsold -> 1.4724522 | C44: =$A44*Prof2-(1-$A44)*Rent_Unsold -> -2.2775478 | D44: =$A44*Prof3-(1-$A44)*Rent_Unsold -> -6.0275478
A45: 0.5 | B45: =$A45*Prof1-(1-$A45)*Rent_Unsold -> 2.7220772 | C45: =$A45*Prof2-(1-$A45)*Rent_Unsold -> -2.2779228 | D45: =$A45*Prof3-(1-$A45)*Rent_Unsold -> -7.2779228
A46: Break-even sell-through | B46: =IF(Prof1+Rent_Unsold<=0,"Never",Rent_Unsold/(Prof1+Rent_Unsold)) -> 0.22771059 | C46: =IF(Prof2+Rent_Unsold<=0,"Never",Rent_Unsold/(Prof2+Rent_Unsold)) -> Never | D46: =IF(Prof3+Rent_Unsold<=0,"Never",Rent_Unsold/(Prof3+Rent_Unsold)) -> Never
A48: E. Check: does the rent charged match the rent actually paid?
B49: ₹35 case
A50: Rent actually paid per hub per month | B50: =Rent_Hub -> 10000
A51: Rent charged to parcels per hub per month, at 37.5% sell-through | B51: =Routed_Hub*(ST_M36*Rent_Sold+(1-ST_M36)*Rent_Unsold) -> 10000
A52: Over- or under-charged | B52: =B51/Rent_Hub -> 1
A54: F. India-wide volume
A55: Parcels routed into Hypersale per day | B55: =Routed_Day -> 395357.14
A56: Parcels routed per month | B56: =Routed_D_P*365/12 -> 12025446
A57: Running cost per month | B57: =C_Maint+C_Support -> 600000
A58: One-time build cost | B58: =OneTime -> 10200000
A60: G. Sell-through ramp and monthly profit
A61: Sell-through climbs in a straight line from 5% in month 1 to 20% at month 12, then on to 37.5% at month 36.
A62: Month | B62: Sell-through | C62: Parcels routed | D62: Sales | E62: Net — ₹35 | F62: Cum. — ₹35 | G62: Net — ₹40 | H62: Cum. — ₹40 | I62: Net — ₹45 | J62: Cum. — ₹45 | K62: Reverse trips avoided
A63: 1 | B63: =IF(A63<=12,ST_M1+(ST_M12-ST_M1)*(A63-1)/11,ST_M12+(ST_M36-ST_M12)*(A63-12)/24) -> 0.05 | C63: =Routed_M_P -> 12025446 | D63: =C63*B63 -> 601272.32 | E63: =(C63*(B63*Prof1-(1-B63)*Rent_Unsold)-Maint_P-IF(A63=1,OneTime_P,0))/10^7 -> -3.2164081 | F63: =E63 -> -3.2164081 | G63: =(C63*(B63*Prof2-(1-B63)*Rent_Unsold)-Maint_P-IF(A63=1,OneTime_P,0))/10^7 -> -3.8176804 | H63: =G63 -> -3.8176804 | I63: =(C63*(B63*Prof3-(1-B63)*Rent_Unsold)-Maint_P-IF(A63=1,OneTime_P,0))/10^7 -> -4.4189527 | J63: =I63 -> -4.4189527 | K63: =D63*Reverse/10^7 -> 1.7436897
A64: 2 | B64: =IF(A64<=12,ST_M1+(ST_M12-ST_M1)*(A64-1)/11,ST_M12+(ST_M36-ST_M12)*(A64-12)/24) -> 0.063636364 | C64: =Routed_M_P -> 12025446 | D64: =C64*B64 -> 765255.68 | E64: =(C64*(B64*Prof1-(1-B64)*Rent_Unsold)-Maint_P-IF(A64=1,OneTime_P,0))/10^7 -> -2.0324739 | F64: =F63+E64 -> -5.248882 | G64: =(C64*(B64*Prof2-(1-B64)*Rent_Unsold)-Maint_P-IF(A64=1,OneTime_P,0))/10^7 -> -2.7977296 | H64: =H63+G64 -> -6.61541 | I64: =(C64*(B64*Prof3-(1-B64)*Rent_Unsold)-Maint_P-IF(A64=1,OneTime_P,0))/10^7 -> -3.5629853 | J64: =J63+I64 -> -7.981938 | K64: =D64*Reverse/10^7 -> 2.2192415
A65: 3 | B65: =IF(A65<=12,ST_M1+(ST_M12-ST_M1)*(A65-1)/11,ST_M12+(ST_M36-ST_M12)*(A65-12)/24) -> 0.077272727 | C65: =Routed_M_P -> 12025446 | D65: =C65*B65 -> 929239.04 | E65: =(C65*(B65*Prof1-(1-B65)*Rent_Unsold)-Maint_P-IF(A65=1,OneTime_P,0))/10^7 -> -1.8685397 | F65: =F64+E65 -> -7.1174217 | G65: =(C65*(B65*Prof2-(1-B65)*Rent_Unsold)-Maint_P-IF(A65=1,OneTime_P,0))/10^7 -> -2.7977788 | H65: =H64+G65 -> -9.4131887 | I65: =(C65*(B65*Prof3-(1-B65)*Rent_Unsold)-Maint_P-IF(A65=1,OneTime_P,0))/10^7 -> -3.7270178 | J65: =J64+I65 -> -11.708956 | K65: =D65*Reverse/10^7 -> 2.6947932
A66: 4 | B66: =IF(A66<=12,ST_M1+(ST_M12-ST_M1)*(A66-1)/11,ST_M12+(ST_M36-ST_M12)*(A66-12)/24) -> 0.090909091 | C66: =Routed_M_P -> 12025446 | D66: =C66*B66 -> 1093222.4 | E66: =(C66*(B66*Prof1-(1-B66)*Rent_Unsold)-Maint_P-IF(A66=1,OneTime_P,0))/10^7 -> -1.7046056 | F66: =F65+E66 -> -8.8220272 | G66: =(C66*(B66*Prof2-(1-B66)*Rent_Unsold)-Maint_P-IF(A66=1,OneTime_P,0))/10^7 -> -2.797828 | H66: =H65+G66 -> -12.211017 | I66: =(C66*(B66*Prof3-(1-B66)*Rent_Unsold)-Maint_P-IF(A66=1,OneTime_P,0))/10^7 -> -3.8910504 | J66: =J65+I66 -> -15.600006 | K66: =D66*Reverse/10^7 -> 3.170345
A67: 5 | B67: =IF(A67<=12,ST_M1+(ST_M12-ST_M1)*(A67-1)/11,ST_M12+(ST_M36-ST_M12)*(A67-12)/24) -> 0.10454545 | C67: =Routed_M_P -> 12025446 | D67: =C67*B67 -> 1257205.8 | E67: =(C67*(B67*Prof1-(1-B67)*Rent_Unsold)-Maint_P-IF(A67=1,OneTime_P,0))/10^7 -> -1.5406714 | F67: =F66+E67 -> -10.362699 | G67: =(C67*(B67*Prof2-(1-B67)*Rent_Unsold)-Maint_P-IF(A67=1,OneTime_P,0))/10^7 -> -2.7978772 | H67: =H66+G67 -> -15.008894 | I67: =(C67*(B67*Prof3-(1-B67)*Rent_Unsold)-Maint_P-IF(A67=1,OneTime_P,0))/10^7 -> -4.0550829 | J67: =J66+I67 -> -19.655089 | K67: =D67*Reverse/10^7 -> 3.6458967
A68: 6 | B68: =IF(A68<=12,ST_M1+(ST_M12-ST_M1)*(A68-1)/11,ST_M12+(ST_M36-ST_M12)*(A68-12)/24) -> 0.11818182 | C68: =Routed_M_P -> 12025446 | D68: =C68*B68 -> 1421189.1 | E68: =(C68*(B68*Prof1-(1-B68)*Rent_Unsold)-Maint_P-IF(A68=1,OneTime_P,0))/10^7 -> -1.3767372 | F68: =F67+E68 -> -11.739436 | G68: =(C68*(B68*Prof2-(1-B68)*Rent_Unsold)-Maint_P-IF(A68=1,OneTime_P,0))/10^7 -> -2.7979264 | H68: =H67+G68 -> -17.80682 | I68: =(C68*(B68*Prof3-(1-B68)*Rent_Unsold)-Maint_P-IF(A68=1,OneTime_P,0))/10^7 -> -4.2191155 | J68: =J67+I68 -> -23.874205 | K68: =D68*Reverse/10^7 -> 4.1214485
A69: 7 | B69: =IF(A69<=12,ST_M1+(ST_M12-ST_M1)*(A69-1)/11,ST_M12+(ST_M36-ST_M12)*(A69-12)/24) -> 0.13181818 | C69: =Routed_M_P -> 12025446 | D69: =C69*B69 -> 1585172.5 | E69: =(C69*(B69*Prof1-(1-B69)*Rent_Unsold)-Maint_P-IF(A69=1,OneTime_P,0))/10^7 -> -1.2128031 | F69: =F68+E69 -> -12.952239 | G69: =(C69*(B69*Prof2-(1-B69)*Rent_Unsold)-Maint_P-IF(A69=1,OneTime_P,0))/10^7 -> -2.7979756 | H69: =H68+G69 -> -20.604796 | I69: =(C69*(B69*Prof3-(1-B69)*Rent_Unsold)-Maint_P-IF(A69=1,OneTime_P,0))/10^7 -> -4.383148 | J69: =J68+I69 -> -28.257353 | K69: =D69*Reverse/10^7 -> 4.5970002
A70: 8 | B70: =IF(A70<=12,ST_M1+(ST_M12-ST_M1)*(A70-1)/11,ST_M12+(ST_M36-ST_M12)*(A70-12)/24) -> 0.14545455 | C70: =Routed_M_P -> 12025446 | D70: =C70*B70 -> 1749155.8 | E70: =(C70*(B70*Prof1-(1-B70)*Rent_Unsold)-Maint_P-IF(A70=1,OneTime_P,0))/10^7 -> -1.0488689 | F70: =F69+E70 -> -14.001108 | G70: =(C70*(B70*Prof2-(1-B70)*Rent_Unsold)-Maint_P-IF(A70=1,OneTime_P,0))/10^7 -> -2.7980247 | H70: =H69+G70 -> -23.402821 | I70: =(C70*(B70*Prof3-(1-B70)*Rent_Unsold)-Maint_P-IF(A70=1,OneTime_P,0))/10^7 -> -4.5471806 | J70: =J69+I70 -> -32.804533 | K70: =D70*Reverse/10^7 -> 5.0725519
A71: 9 | B71: =IF(A71<=12,ST_M1+(ST_M12-ST_M1)*(A71-1)/11,ST_M12+(ST_M36-ST_M12)*(A71-12)/24) -> 0.15909091 | C71: =Routed_M_P -> 12025446 | D71: =C71*B71 -> 1913139.2 | E71: =(C71*(B71*Prof1-(1-B71)*Rent_Unsold)-Maint_P-IF(A71=1,OneTime_P,0))/10^7 -> -0.88493474 | F71: =F70+E71 -> -14.886043 | G71: =(C71*(B71*Prof2-(1-B71)*Rent_Unsold)-Maint_P-IF(A71=1,OneTime_P,0))/10^7 -> -2.7980739 | H71: =H70+G71 -> -26.200894 | I71: =(C71*(B71*Prof3-(1-B71)*Rent_Unsold)-Maint_P-IF(A71=1,OneTime_P,0))/10^7 -> -4.7112131 | J71: =J70+I71 -> -37.515746 | K71: =D71*Reverse/10^7 -> 5.5481037
A72: 10 | B72: =IF(A72<=12,ST_M1+(ST_M12-ST_M1)*(A72-1)/11,ST_M12+(ST_M36-ST_M12)*(A72-12)/24) -> 0.17272727 | C72: =Routed_M_P -> 12025446 | D72: =C72*B72 -> 2077122.6 | E72: =(C72*(B72*Prof1-(1-B72)*Rent_Unsold)-Maint_P-IF(A72=1,OneTime_P,0))/10^7 -> -0.72100057 | F72: =F71+E72 -> -15.607043 | G72: =(C72*(B72*Prof2-(1-B72)*Rent_Unsold)-Maint_P-IF(A72=1,OneTime_P,0))/10^7 -> -2.7981231 | H72: =H71+G72 -> -28.999018 | I72: =(C72*(B72*Prof3-(1-B72)*Rent_Unsold)-Maint_P-IF(A72=1,OneTime_P,0))/10^7 -> -4.8752457 | J72: =J71+I72 -> -42.390992 | K72: =D72*Reverse/10^7 -> 6.0236554
A73: 11 | B73: =IF(A73<=12,ST_M1+(ST_M12-ST_M1)*(A73-1)/11,ST_M12+(ST_M36-ST_M12)*(A73-12)/24) -> 0.18636364 | C73: =Routed_M_P -> 12025446 | D73: =C73*B73 -> 2241105.9 | E73: =(C73*(B73*Prof1-(1-B73)*Rent_Unsold)-Maint_P-IF(A73=1,OneTime_P,0))/10^7 -> -0.55706641 | F73: =F72+E73 -> -16.16411 | G73: =(C73*(B73*Prof2-(1-B73)*Rent_Unsold)-Maint_P-IF(A73=1,OneTime_P,0))/10^7 -> -2.7981723 | H73: =H72+G73 -> -31.79719 | I73: =(C73*(B73*Prof3-(1-B73)*Rent_Unsold)-Maint_P-IF(A73=1,OneTime_P,0))/10^7 -> -5.0392783 | J73: =J72+I73 -> -47.43027 | K73: =D73*Reverse/10^7 -> 6.4992072
A74: 12 | B74: =IF(A74<=12,ST_M1+(ST_M12-ST_M1)*(A74-1)/11,ST_M12+(ST_M36-ST_M12)*(A74-12)/24) -> 0.2 | C74: =Routed_M_P -> 12025446 | D74: =C74*B74 -> 2405089.3 | E74: =(C74*(B74*Prof1-(1-B74)*Rent_Unsold)-Maint_P-IF(A74=1,OneTime_P,0))/10^7 -> -0.39313224 | F74: =F73+E74 -> -16.557242 | G74: =(C74*(B74*Prof2-(1-B74)*Rent_Unsold)-Maint_P-IF(A74=1,OneTime_P,0))/10^7 -> -2.7982215 | H74: =H73+G74 -> -34.595411 | I74: =(C74*(B74*Prof3-(1-B74)*Rent_Unsold)-Maint_P-IF(A74=1,OneTime_P,0))/10^7 -> -5.2033108 | J74: =J73+I74 -> -52.633581 | K74: =D74*Reverse/10^7 -> 6.9747589
A75: 13 | B75: =IF(A75<=12,ST_M1+(ST_M12-ST_M1)*(A75-1)/11,ST_M12+(ST_M36-ST_M12)*(A75-12)/24) -> 0.20729167 | C75: =Routed_M_P -> 12025446 | D75: =C75*B75 -> 2492774.8 | E75: =(C75*(B75*Prof1-(1-B75)*Rent_Unsold)-Maint_P-IF(A75=1,OneTime_P,0))/10^7 -> -0.305473 | F75: =F74+E75 -> -16.862715 | G75: =(C75*(B75*Prof2-(1-B75)*Rent_Unsold)-Maint_P-IF(A75=1,OneTime_P,0))/10^7 -> -2.7982478 | H75: =H74+G75 -> -37.393659 | I75: =(C75*(B75*Prof3-(1-B75)*Rent_Unsold)-Maint_P-IF(A75=1,OneTime_P,0))/10^7 -> -5.2910227 | J75: =J74+I75 -> -57.924604 | K75: =D75*Reverse/10^7 -> 7.229047
... A98: 36 | B98: =IF(A98<=12,ST_M1+(ST_M12-ST_M1)*(A98-1)/11,ST_M12+(ST_M36-ST_M12)*(A98-12)/24) -> 0.375 | C98: =Routed_M_P -> 12025446 | D98: =C98*B98 -> 4509542.4 | E98: =(C98*(B98*Prof1-(1-B98)*Rent_Unsold)-Maint_P-IF(A98=1,OneTime_P,0))/10^7 -> 1.7106895 | F98: =F97+E98 -> 0.30535677 | G98: =(C98*(B98*Prof2-(1-B98)*Rent_Unsold)-Maint_P-IF(A98=1,OneTime_P,0))/10^7 -> -2.7988529 | H98: =H97+G98 -> -101.76062 | I98: =(C98*(B98*Prof3-(1-B98)*Rent_Unsold)-Maint_P-IF(A98=1,OneTime_P,0))/10^7 -> -7.3083953 | J98: =J97+I98 -> -203.8266 | K98: =D98*Reverse/10^7 -> 13.077673
A100: H. Results by year
B101: Year 1 | C101: Year 2 | D101: Year 3 | E101: 3-year total
A102: Average sell-through | B102: =AVERAGE(B63:B74) -> 0.125 | C102: =AVERAGE(B75:B86) -> 0.24739583 | D102: =AVERAGE(B87:B98) -> 0.33489583
A103: Hypersale sales | B103: =SUM(D63:D74)/10^5 -> 180.3817 | C103: =SUM(D75:D86)/10^5 -> 357.00544 | D103: =SUM(D87:D98)/10^5 -> 483.27263 | E103: =SUM(D63:D98)/10^5 -> 1020.6598
A104: Net profit — ₹35 | B104: =SUM(E63:E74) -> -16.557242 | C104: =SUM(E75:E86) -> 2.1198339 | D104: =SUM(E87:E98) -> 14.742765 | E104: =SUM(E63:E98) -> 0.30535677
A105: Net profit — ₹40 | B105: =SUM(G63:G74) -> -34.595411 | C105: =SUM(G75:G86) -> -33.58071 | D105: =SUM(G87:G98) -> -33.584498 | E105: =SUM(G63:G98) -> -101.76062
A106: Net profit — ₹45 | B106: =SUM(I63:I74) -> -52.633581 | C106: =SUM(I75:I86) -> -69.281254 | D106: =SUM(I87:I98) -> -81.911761 | E106: =SUM(I63:I98) -> -203.8266
A107: MEMO: reverse trips avoided (not in profit) | B107: =SUM(K63:K74) -> 52.310692 | C107: =SUM(K75:K86) -> 103.53158 | D107: =SUM(K87:K98) -> 140.14906 | E107: =SUM(K63:K98) -> 295.99133
A108: Payback month — ₹35 / ₹40 / ₹45 | B108: =IF(F98<0,"Beyond 36",COUNTIF(F63:F98,"<0")+1) -> 36 | C108: =IF(H98<0,"Beyond 36",COUNTIF(H63:H98,"<0")+1) -> Beyond 36 | D108: =IF(J98<0,"Beyond 36",COUNTIF(J63:J98,"<0")+1) -> Beyond 36
A109: Profit per sale once the ramp is done (month 36) | B109: =Prof1 -> 7.7205772 | C109: =Prof2 -> -2.2794228 | D109: =Prof3 -> -12.279423
A111: I. Operational break-even and payback — extended to 120 months
A112: A. Profit only — fees minus costs (as in sections 3–8) | B112: ₹35 case | C112: ₹40 case | D112: ₹45 case
A113: Profit per sale once the ramp is done | B113: =Prof1 -> 7.7205772 | C113: =Prof2 -> -2.2794228 | D113: =Prof3 -> -12.279423
A114: Sell-through assumed after month 36 | B114: =ST_M36 -> 0.375 | C114: =ST_M36 -> 0.375 | D114: =ST_M36 -> 0.375
A115: Sell-through needed to cover the monthly running cost | B115: =IF(Prof1+Rent_Unsold<=0,"Never",IF((Rent_Unsold+Maint_P/Routed_M_P)/(Prof1+Rent_Unsold)>1,"Above 100%",(Rent_Unsold+Maint_P/Routed_M_P)/(Prof1+Rent_Unsold))) -> 0.23270151 | C115: =IF(Prof2+Rent_Unsold<=0,"Never",IF((Rent_Unsold+Maint_P/Routed_M_P)/(Prof2+Rent_Unsold)>1,"Above 100%",(Rent_Unsold+Maint_P/Routed_M_P)/(Prof2+Rent_Unsold))) -> Never | D115: =IF(Prof3+Rent_Unsold<=0,"Never",IF((Rent_Unsold+Maint_P/Routed_M_P)/(Prof3+Rent_Unsold)>1,"Above 100%",(Rent_Unsold+Maint_P/Routed_M_P)/(Prof3+Rent_Unsold))) -> Never
A116: Operational break-even month | B116: =IF(COUNTIF($D$224:$D$343,">0")=0,"Beyond 120",COUNTIF($D$224:$D$343,"<=0")+1) -> 17 | C116: =IF(COUNTIF($E$224:$E$343,">0")=0,"Beyond 120",COUNTIF($E$224:$E$343,"<=0")+1) -> Beyond 120 | D116: =IF(COUNTIF($F$224:$F$343,">0")=0,"Beyond 120",COUNTIF($F$224:$F$343,"<=0")+1) -> Beyond 120
A117: …which is | B117: =IF(ISNUMBER(B116),"Year "&(INT((B116-1)/12)+1)&", month "&(MOD(B116-1,12)+1),"–") -> Year 2, month 5 | C117: =IF(ISNUMBER(C116),"Year "&(INT((C116-1)/12)+1)&", month "&(MOD(C116-1,12)+1),"–") -> – | D117: =IF(ISNUMBER(D116),"Year "&(INT((D116-1)/12)+1)&", month "&(MOD(D116-1,12)+1),"–") -> –
A118: Payback month (build cost recovered) | B118: =IF(MAX($G$224:$G$343)<0,"Beyond 120",COUNTIF($G$224:$G$343,"<0")+1) -> 36 | C118: =IF(MAX($H$224:$H$343)<0,"Beyond 120",COUNTIF($H$224:$H$343,"<0")+1) -> Beyond 120 | D118: =IF(MAX($I$224:$I$343)<0,"Beyond 120",COUNTIF($I$224:$I$343,"<0")+1) -> Beyond 120
A119: …which is | B119: =IF(ISNUMBER(B118),"Year "&(INT((B118-1)/12)+1)&", month "&(MOD(B118-1,12)+1),"–") -> Year 3, month 12 | C119: =IF(ISNUMBER(C118),"Year "&(INT((C118-1)/12)+1)&", month "&(MOD(C118-1,12)+1),"–") -> – | D119: =IF(ISNUMBER(D118),"Year "&(INT((D118-1)/12)+1)&", month "&(MOD(D118-1,12)+1),"–") -> –
A120: Deepest cumulative loss (cash tied up before it turns) | B120: =MIN($G$224:$G$343) -> -17.253178 | C120: =MIN($H$224:$H$343) -> -336.86426 | D120: =MIN($I$224:$I$343) -> -817.7318
A121: …reached in month | B121: =MATCH(MIN($G$224:$G$343),$G$224:$G$343,0) -> 16 | C121: =MATCH(MIN($H$224:$H$343),$H$224:$H$343,0) -> 120 | D121: =MATCH(MIN($I$224:$I$343),$I$224:$I$343,0) -> 120
A122: Cumulative profit at month 120 | B122: {=INDEX($G$224:$G$343,120)} -> 144.00328 | C122: {=INDEX($H$224:$H$343,120)} -> -336.86426 | D122: {=INDEX($I$224:$I$343,120)} -> -817.7318
A123: B. Also counting the RTO cost saved on every sale | B123: ₹35 case | C123: ₹40 case | D123: ₹45 case
A124: Share of 'other RTO costs' (₹62) avoided when a parcel sells | B124: 1
A125: RTO cost avoided per parcel that sells (reverse trip + other costs) | B125: =Reverse+Leg_Other*$B$124 -> 120 | C125: =Reverse+Leg_Other*$B$124 -> 120 | D125: =Reverse+Leg_Other*$B$124 -> 120
A126: Sell-through needed to cover the monthly running cost | B126: =IF(Prof1+RTO_Avoid_Sale+Rent_Unsold<=0,"Never",IF((Rent_Unsold+Maint_P/Routed_M_P)/(Prof1+RTO_Avoid_Sale+Rent_Unsold)>1,"Above 100%",(Rent_Unsold+Maint_P/Routed_M_P)/(Prof1+RTO_Avoid_Sale+Rent_Unsold))) -> 0.017895159 | C126: =IF(Prof2+RTO_Avoid_Sale+Rent_Unsold<=0,"Never",IF((Rent_Unsold+Maint_P/Routed_M_P)/(Prof2+RTO_Avoid_Sale+Rent_Unsold)>1,"Above 100%",(Rent_Unsold+Maint_P/Routed_M_P)/(Prof2+RTO_Avoid_Sale+Rent_Unsold))) -> 0.019386459 | D126: =IF(Prof3+RTO_Avoid_Sale+Rent_Unsold<=0,"Never",IF((Rent_Unsold+Maint_P/Routed_M_P)/(Prof3+RTO_Avoid_Sale+Rent_Unsold)>1,"Above 100%",(Rent_Unsold+Maint_P/Routed_M_P)/(Prof3+RTO_Avoid_Sale+Rent_Unsold))) -> 0.021148913
A127: Operational break-even month | B127: =IF(SUMPRODUCT(--($D$224:$D$343+Routed_M_P*$B$224:$B$343*RTO_Avoid_Sale/10^7>0))=0,"Beyond 120",SUMPRODUCT(--($D$224:$D$343+Routed_M_P*$B$224:$B$343*RTO_Avoid_Sale/10^7<=0))+1) -> 1 | C127: =IF(SUMPRODUCT(--($E$224:$E$343+Routed_M_P*$B$224:$B$343*RTO_Avoid_Sale/10^7>0))=0,"Beyond 120",SUMPRODUCT(--($E$224:$E$343+Routed_M_P*$B$224:$B$343*RTO_Avoid_Sale/10^7<=0))+1) -> 1 | D127: =IF(SUMPRODUCT(--($F$224:$F$343+Routed_M_P*$B$224:$B$343*RTO_Avoid_Sale/10^7>0))=0,"Beyond 120",SUMPRODUCT(--($F$224:$F$343+Routed_M_P*$B$224:$B$343*RTO_Avoid_Sale/10^7<=0))+1) -> 1
A128: …which is | B128: =IF(ISNUMBER(B127),"Year "&(INT((B127-1)/12)+1)&", month "&(MOD(B127-1,12)+1),"–") -> Year 1, month 1 | C128: =IF(ISNUMBER(C127),"Year "&(INT((C127-1)/12)+1)&", month "&(MOD(C127-1,12)+1),"–") -> Year 1, month 1 | D128: =IF(ISNUMBER(D127),"Year "&(INT((D127-1)/12)+1)&", month "&(MOD(D127-1,12)+1),"–") -> Year 1, month 1
A129: Payback month (build cost recovered) | B129: =IF(MAX($J$224:$J$343)<0,"Beyond 120",COUNTIF($J$224:$J$343,"<0")+1) -> 1 | C129: =IF(MAX($K$224:$K$343)<0,"Beyond 120",COUNTIF($K$224:$K$343,"<0")+1) -> 1 | D129: =IF(MAX($L$224:$L$343)<0,"Beyond 120",COUNTIF($L$224:$L$343,"<0")+1) -> 1
...

Sheet Unit Economics
A1: Unit economics — one RTO parcel
A2: A. What one RTO costs today
A3: Cost leg | B3: ₹ per RTO | F3: How it's calculated
A4: Forward trip to the last-mile hub | B4: =N_FMHub+N_FMCart+N_FMSC+N_NLH+N_LMSC+N_RLH -> 29 | F4: Sum of the six case-pack node costs before last mile
A5: Failed last-mile attempt | B5: 0 | F5: LMDC node cost
A6: Reverse trip back to the seller | B6: =Reverse -> 29 | F6: Team assumption: retraces the forward path
A7: Other RTO costs (not broken down in the pack) | B7: =62+29 -> 91 | F7: Residual: ₹120 minus the three legs above
A8: Total cost of one RTO today | B8: =SUM(B4:B7) -> 149
A10: B. One RTO parcel: today vs Hypersale
A11: Line item (₹ per parcel) | B11: Today: return to seller | C11: Hypersale: sold (₹35 base) | D11: Hypersale: sold (₹45 high) | E11: Hypersale: not sold in 7 days | F11: Note
A12: Forward trip (already spent) | F12: Same in every case
A13: Failed attempt (already spent) | B13: 0 | C13: 0 | D13: 0 | E13: 0 | F13: Same in every case
A14: Reverse trip to seller | B14: =-Leg_Reverse -> -29 | C14: 0 | D14: 0 | E14: =-Leg_Reverse -> -29 | F14: Avoided only when the item sells
A15: Other RTO costs | B15: =-Leg_Other -> -91 | C15: 0 | D15: 0 | E15: =-Leg_Other -> -91 | F15: Share avoided is a missing input (0%)
A16: Routing + repack + delivery to new buyer | B16: 0 | C16: =-Route_Base -> -35 | D16: =-Route_High -> -45 | E16: 0 | F16: ₹35 / ₹45 (breakup in section 3)
A17: Extra cost for buyers at another hub (avg) | B17: 0 | E17: 0 | F17: Tier B share × extra cost (section 4)
A18: Listing / QC handling | B18: 0 | C18: =-Handling -> 0 | D18: =-Handling -> 0 | E18: =-Handling -> 0 | F18: Missing input (0)
A19: Holding on the shelf | B19: 0 | C19: =-Hold_Day -> -2.2764228 | D19: =-Hold_Day -> -2.2764228 | E19: =-Hold_Day -> -2.2764228 | F19: Missing input (0)
A20: Total cost | B20: =SUM(B12:B19) -> -120 | C20: =SUM(C12:C19) -> -37.276423 | D20: =SUM(D12:D19) -> -47.276423 | E20: =SUM(E12:E19) -> -122.27642
A21: Customer express fee | B21: 0 | C21: =AOV*Fee_Express -> 15 | D21: =AOV*Fee_Express -> 15 | E21: 0 | F21: Paid only on a Hypersale sale
A22: Seller protection fee | B22: 0 | C22: =AOV*Fee_Seller -> 29.997 | D22: =AOV*Fee_Seller -> 29.997 | E22: 0 | F22: Paid only on a Hypersale sale
A23: NET cost per parcel | B23: =B20+B21+B22 -> -120 | C23: =C20+C21+C22 -> 7.7205772 | D23: =D20+D21+D22 -> -2.2794228 | E23: =E20+E21+E22 -> -122.27642
A24: Saving vs today | B24: =B23-$B$23 -> 0 | C24: =C23-$B$23 -> 127.72058 | D24: =D23-$B$23 -> 117.72058 | E24: =E23-$B$23 -> -2.2764228
A26: C. What's inside the ₹35 / ₹45 routing cost
A27: Component | B27: ₹ per sale | F27: Source
A28: Last-mile delivery to the new buyer | B28: =N_LMDC -> 14 | F28: Case data pack LMDC node
A29: Payment gateway (on price + express fee) | B29: =Gateway*(AOV+AOV*Fee_Express) -> 6.726 | F29: Razorpay 2.36%
A30: New courier bag | B30: =Bag -> 1.5 | F30: IndiaMART
A31: New label | B31: =Label -> 1 | F31: IndiaMART
A32: Sourced components | B32: =SUM(B28:B31) -> 23.226
A33: Left for hub labour, re-sort, support — base / high | B33: =Route_Base-Route_Sourced -> 11.774 | C33: =Route_High-Route_Sourced -> 21.774 | F33: Base in column C, high in column D
A34: …which buys this many minutes of hub staff time — base / high | B34: =(Route_Base-Route_Sourced)/(Wage/(26*8*60)) -> 9.795968 | C34: =(Route_High-Route_Sourced)/(Wage/(26*8*60)) -> 18.115968 | F34: Wage ÷ (26 days × 8 h × 60 min). A hub time-check settles which case is closer.
A36: D. Remote hubs — how far can the radius extend?
A37: Where the buyer is | B37: Extra last mile | C37: Transfer cost | D37: Saving per sale — ₹35 | E37: Saving per sale — ₹45 | F37: Extend the radius here?
A38: A — same hub (local) | B38: =0 -> 0 | C38: =0 -> 0 | D38: =Save_Sold_Base+Remote_Uplift-B38-C38 -> 134.22058 | E38: =Save_Sold_High+Remote_Uplift-B38-C38 -> 124.22058 | F38: =IF(ROUND(E38,2)>0,"Yes",IF(D38>0,"Base case only (break-even at ₹45)","No — return to seller")) -> Yes
A39: B — another hub, same sort centre | B39: =LM_Remote-N_LMDC -> 11 | C39: =N_RLH+N_LMSC+N_RLH -> 15 | D39: =Save_Sold_Base+Remote_Uplift-B39-C39 -> 108.22058 | E39: =Save_Sold_High+Remote_Uplift-B39-C39 -> 98.220577 | F39: =IF(ROUND(E39,2)>0,"Yes",IF(D39>0,"Base case only (break-even at ₹45)","No — return to seller")) -> Yes
A40: C — a hub in another city | B40: =LM_Remote-N_LMDC -> 11 | C40: =N_RLH+N_LMSC+N_NLH+N_LMSC+N_RLH -> 28 | D40: =Save_Sold_Base+Remote_Uplift-B40-C40 -> 95.220577 | E40: =Save_Sold_High+Remote_Uplift-B40-C40 -> 85.220577 | F40: =IF(ROUND(E40,2)>0,"Yes",IF(D40>0,"Base case only (break-even at ₹45)","No — return to seller")) -> Yes
A41: Average extra cost per sale (Tier B share × Tier B extra cost) | B41: =TierB_Share*(TierB_Extra+TierB_Transfer) -> 6.5 | F41: Tier B share is a missing input (0%) — see Scenarios

Sheet India Rollout
A1: India rollout — volume, costs and 3-year results
A2: A. How many parcels go into Hypersale
A3: Blended RTO rate | B3: =COD_Share*RTO_COD+(1-COD_Share)*RTO_Prepaid -> 0.17 | C3: 80% × 20% + 20% × 5%
A4: RTO parcels per day | B4: =Orders*RTO_Rate -> 714000 | C4: Orders × RTO rate
A5: RTO parcels per day of which eligible for Hypersale | B5: =RTO_Day*Eligible -> 642600 | C5: × 90% eligible
A6: Shelf capacity across all hubs, per day | B6: =Hubs*Shelf/7 -> 395357.14 | C6: 2,700 hubs × 500 per week ÷ 7
A7: Parcels routed into Hypersale per day | B7: =MIN(Elig_Day,Cap_Day) -> 395357.14 | C7: The lower of the two
A8: What limits volume? | B8: =IF(Elig_Day>Cap_Day,"Shelf space","Eligible parcels") -> Shelf space | C8: More shelf/kirana hold space raises volume if shelf-limited
A10: B. Setup and running costs
A11: One-time: app/site build + cloud setup | B11: =C_Build+C_Cloud -> 10200000
A12: One-time: hub equipment (scanner + racks + training) × hubs | B12: =Hubs*(C_Scanner+C_Racks+C_Training+Printer_Note) -> 0
A13: TOTAL one-time cost (charged in month 1) | B13: =OneTime_Central+OneTime_Hubs -> 10200000
A14: Monthly running: maintenance + support + per-hub costs × hubs | B14: =C_Maint+C_Support+C_HubMonthly*Hubs -> 600000
A16: C. Results by year
B17: Year 1 | C17: Year 2 | D17: Year 3 | E17: 3-year total
A18: Average sell-through | B18: =AVERAGE(B29:B40) -> 0.2375 | C18: =AVERAGE(B41:B52) -> 0.375 | D18: =AVERAGE(B53:B64) -> 0.375
A19: RTO parcels saved from the reverse trip | B19: =SUM(D29:D40)/10^5 -> 342.72522 | C19: =SUM(D41:D52)/10^5 -> 541.14509 | D19: =SUM(D53:D64)/10^5 -> 541.14509 | E19: =SUM(D29:D64)/10^5 -> 1425.0154
A20: Share of all RTO parcels saved | B20: =SUM(D29:D40)/(RTO_Day*365) -> 0.13150885 | C20: =SUM(D41:D52)/(RTO_Day*365) -> 0.20764556 | D20: =SUM(D53:D64)/(RTO_Day*365) -> 0.20764556 | E20: =SUM(D29:D64)/(RTO_Day*365*3) -> 0.18226666
A21: Net profit — ₹35 base | B21: =SUM(I29:I40) -> 410.94251 | C21: =SUM(I41:I52) -> 669.90238 | D21: =SUM(I53:I64) -> 669.90238 | E21: =SUM(I29:I64) -> 1750.7473
A22: Net profit — ₹45 high | B22: =SUM(K29:K40) -> 376.66999 | C22: =SUM(K41:K52) -> 615.78787 | D22: =SUM(K53:K64) -> 615.78787 | E22: =SUM(K29:K64) -> 1608.2457
A23: Payback month — ₹35 base / ₹45 high | B23: =IF(J64<0,"Beyond 36",COUNTIF(J29:J64,"<0")+1) -> 1 | C23: =IF(L64<0,"Beyond 36",COUNTIF(L29:L64,"<0")+1) -> 1
A24: Today's total Valmo RTO cost per year (for scale) | B24: =RTO_Day*365*RTO_Total/10^7 -> 3127.32
A27: D. Month-by-month detail
A28: Month | B28: Sell-through | C28: Parcels routed | D28: Sold = RTO saved | E28: Saving — ₹35 | F28: Saving — ₹45 | G28: Running cost | H28: One-time cost | I28: Net — ₹35 | J28: Cumulative — ₹35 | K28: Net — ₹45 | L28: Cumulative — ₹45
A29: 1 | B29: =IF(A29>=Ramp,ST_Target,ST_Start+(ST_Target-ST_Start)*(A29-1)/MAX(1,Ramp-1)) -> 0.1 | C29: =Routed_Day*365/12 -> 12025446 | D29: =C29*B29 -> 1202544.6 | E29: =C29*(B29*Save_Sold_Base+(1-B29)*Save_Unsold)/10^7 -> 12.89522 | F29: =C29*(B29*Save_Sold_High+(1-B29)*Save_Unsold)/10^7 -> 11.692675 | G29: =-Running_M/10^7 -> -0.06 | H29: =IF(A29=1,-OneTime/10^7,0) -> -1.02 | I29: =E29+G29+H29 -> 11.81522 | J29: =I29 -> 11.81522 | K29: =F29+G29+H29 -> 10.612675 | L29: =K29 -> 10.612675
A30: 2 | B30: =IF(A30>=Ramp,ST_Target,ST_Start+(ST_Target-ST_Start)*(A30-1)/MAX(1,Ramp-1)) -> 0.125 | C30: =Routed_Day*365/12 -> 12025446 | D30: =C30*B30 -> 1503180.8 | E30: =C30*(B30*Save_Sold_Base+(1-B30)*Save_Unsold)/10^7 -> 16.803399 | F30: =C30*(B30*Save_Sold_High+(1-B30)*Save_Unsold)/10^7 -> 15.300219 | G30: =-Running_M/10^7 -> -0.06 | H30: =IF(A30=1,-OneTime/10^7,0) -> 0 | I30: =E30+G30+H30 -> 16.743399 | J30: =J29+I30 -> 28.558619 | K30: =F30+G30+H30 -> 15.240219 | L30: =L29+K30 -> 25.852894
A31: 3 | B31: =IF(A31>=Ramp,ST_Target,ST_Start+(ST_Target-ST_Start)*(A31-1)/MAX(1,Ramp-1)) -> 0.15 | C31: =Routed_Day*365/12 -> 12025446 | D31: =C31*B31 -> 1803817 | E31: =C31*(B31*Save_Sold_Base+(1-B31)*Save_Unsold)/10^7 -> 20.711579 | F31: =C31*(B31*Save_Sold_High+(1-B31)*Save_Unsold)/10^7 -> 18.907762 | G31: =-Running_M/10^7 -> -0.06 | H31: =IF(A31=1,-OneTime/10^7,0) -> 0 | I31: =E31+G31+H31 -> 20.651579 | J31: =J30+I31 -> 49.210198 | K31: =F31+G31+H31 -> 18.847762 | L31: =L30+K31 -> 44.700656
A32: 4 | B32: =IF(A32>=Ramp,ST_Target,ST_Start+(ST_Target-ST_Start)*(A32-1)/MAX(1,Ramp-1)) -> 0.175 | C32: =Routed_Day*365/12 -> 12025446 | D32: =C32*B32 -> 2104453.1 | E32: =C32*(B32*Save_Sold_Base+(1-B32)*Save_Unsold)/10^7 -> 24.619759 | F32: =C32*(B32*Save_Sold_High+(1-B32)*Save_Unsold)/10^7 -> 22.515306 | G32: =-Running_M/10^7 -> -0.06 | H32: =IF(A32=1,-OneTime/10^7,0) -> 0 | I32: =E32+G32+H32 -> 24.559759 | J32: =J31+I32 -> 73.769958 | K32: =F32+G32+H32 -> 22.455306 | L32: =L31+K32 -> 67.155962
A33: 5 | B33: =IF(A33>=Ramp,ST_Target,ST_Start+(ST_Target-ST_Start)*(A33-1)/MAX(1,Ramp-1)) -> 0.2 | C33: =Routed_Day*365/12 -> 12025446 | D33: =C33*B33 -> 2405089.3 | E33: =C33*(B33*Save_Sold_Base+(1-B33)*Save_Unsold)/10^7 -> 28.527939 | F33: =C33*(B33*Save_Sold_High+(1-B33)*Save_Unsold)/10^7 -> 26.12285 | G33: =-Running_M/10^7 -> -0.06 | H33: =IF(A33=1,-OneTime/10^7,0) -> 0 | I33: =E33+G33+H33 -> 28.467939 | J33: =J32+I33 -> 102.2379 | K33: =F33+G33+H33 -> 26.06285 | L33: =L32+K33 -> 93.218812
A34: 6 | B34: =IF(A34>=Ramp,ST_Target,ST_Start+(ST_Target-ST_Start)*(A34-1)/MAX(1,Ramp-1)) -> 0.225 | C34: =Routed_Day*365/12 -> 12025446 | D34: =C34*B34 -> 2705725.4 | E34: =C34*(B34*Save_Sold_Base+(1-B34)*Save_Unsold)/10^7 -> 32.436119 | F34: =C34*(B34*Save_Sold_High+(1-B34)*Save_Unsold)/10^7 -> 29.730394 | G34: =-Running_M/10^7 -> -0.06 | H34: =IF(A34=1,-OneTime/10^7,0) -> 0 | I34: =E34+G34+H34 -> 32.376119 | J34: =J33+I34 -> 134.61402 | K34: =F34+G34+H34 -> 29.670394 | L34: =L33+K34 -> 122.88921
A35: 7 | B35: =IF(A35>=Ramp,ST_Target,ST_Start+(ST_Target-ST_Start)*(A35-1)/MAX(1,Ramp-1)) -> 0.25 | C35: =Routed_Day*365/12 -> 12025446 | D35: =C35*B35 -> 3006361.6 | E35: =C35*(B35*Save_Sold_Base+(1-B35)*Save_Unsold)/10^7 -> 36.344299 | F35: =C35*(B35*Save_Sold_High+(1-B35)*Save_Unsold)/10^7 -> 33.337937 | G35: =-Running_M/10^7 -> -0.06 | H35: =IF(A35=1,-OneTime/10^7,0) -> 0 | I35: =E35+G35+H35 -> 36.284299 | J35: =J34+I35 -> 170.89831 | K35: =F35+G35+H35 -> 33.277937 | L35: =L34+K35 -> 156.16714
A36: 8 | B36: =IF(A36>=Ramp,ST_Target,ST_Start+(ST_Target-ST_Start)*(A36-1)/MAX(1,Ramp-1)) -> 0.275 | C36: =Routed_Day*365/12 -> 12025446 | D36: =C36*B36 -> 3306997.8 | E36: =C36*(B36*Save_Sold_Base+(1-B36)*Save_Unsold)/10^7 -> 40.252479 | F36: =C36*(B36*Save_Sold_High+(1-B36)*Save_Unsold)/10^7 -> 36.945481 | G36: =-Running_M/10^7 -> -0.06 | H36: =IF(A36=1,-OneTime/10^7,0) -> 0 | I36: =E36+G36+H36 -> 40.192479 | J36: =J35+I36 -> 211.09079 | K36: =F36+G36+H36 -> 36.885481 | L36: =L35+K36 -> 193.05262
A37: 9 | B37: =IF(A37>=Ramp,ST_Target,ST_Start+(ST_Target-ST_Start)*(A37-1)/MAX(1,Ramp-1)) -> 0.3 | C37: =Routed_Day*365/12 -> 12025446 | D37: =C37*B37 -> 3607633.9 | E37: =C37*(B37*Save_Sold_Base+(1-B37)*Save_Unsold)/10^7 -> 44.160659 | F37: =C37*(B37*Save_Sold_High+(1-B37)*Save_Unsold)/10^7 -> 40.553025 | G37: =-Running_M/10^7 -> -0.06 | H37: =IF(A37=1,-OneTime/10^7,0) -> 0 | I37: =E37+G37+H37 -> 44.100659 | J37: =J36+I37 -> 255.19145 | K37: =F37+G37+H37 -> 40.493025 | L37: =L36+K37 -> 233.54565
A38: 10 | B38: =IF(A38>=Ramp,ST_Target,ST_Start+(ST_Target-ST_Start)*(A38-1)/MAX(1,Ramp-1)) -> 0.325 | C38: =Routed_Day*365/12 -> 12025446 | D38: =C38*B38 -> 3908270.1 | E38: =C38*(B38*Save_Sold_Base+(1-B38)*Save_Unsold)/10^7 -> 48.068839 | F38: =C38*(B38*Save_Sold_High+(1-B38)*Save_Unsold)/10^7 -> 44.160569 | G38: =-Running_M/10^7 -> -0.06 | H38: =IF(A38=1,-OneTime/10^7,0) -> 0 | I38: =E38+G38+H38 -> 48.008839 | J38: =J37+I38 -> 303.20029 | K38: =F38+G38+H38 -> 44.100569 | L38: =L37+K38 -> 277.64622
A39: 11 | B39: =IF(A39>=Ramp,ST_Target,ST_Start+(ST_Target-ST_Start)*(A39-1)/MAX(1,Ramp-1)) -> 0.35 | C39: =Routed_Day*365/12 -> 12025446 | D39: =C39*B39 -> 4208906.2 | E39: =C39*(B39*Save_Sold_Base+(1-B39)*Save_Unsold)/10^7 -> 51.977019 | F39: =C39*(B39*Save_Sold_High+(1-B39)*Save_Unsold)/10^7 -> 47.768112 | G39: =-Running_M/10^7 -> -0.06 | H39: =IF(A39=1,-OneTime/10^7,0) -> 0 | I39: =E39+G39+H39 -> 51.917019 | J39: =J38+I39 -> 355.11731 | K39: =F39+G39+H39 -> 47.708112 | L39: =L38+K39 -> 325.35433
A40: 12 | B40: =IF(A40>=Ramp,ST_Target,ST_Start+(ST_Target-ST_Start)*(A40-1)/MAX(1,Ramp-1)) -> 0.375 | C40: =Routed_Day*365/12 -> 12025446 | D40: =C40*B40 -> 4509542.4 | E40: =C40*(B40*Save_Sold_Base+(1-B40)*Save_Unsold)/10^7 -> 55.885198 | F40: =C40*(B40*Save_Sold_High+(1-B40)*Save_Unsold)/10^7 -> 51.375656 | G40: =-Running_M/10^7 -> -0.06 | H40: =IF(A40=1,-OneTime/10^7,0) -> 0 | I40: =E40+G40+H40 -> 55.825198 | J40: =J39+I40 -> 410.94251 | K40: =F40+G40+H40 -> 51.315656 | L40: =L39+K40 -> 376.66999
A41: 13 | B41: =IF(A41>=Ramp,ST_Target,ST_Start+(ST_Target-ST_Start)*(A41-1)/MAX(1,Ramp-1)) -> 0.375 | C41: =Routed_Day*365/12 -> 12025446 | D41: =C41*B41 -> 4509542.4 | E41: =C41*(B41*Save_Sold_Base+(1-B41)*Save_Unsold)/10^7 -> 55.885198 | F41: =C41*(B41*Save_Sold_High+(1-B41)*Save_Unsold)/10^7 -> 51.375656 | G41: =-Running_M/10^7 -> -0.06 | H41: =IF(A41=1,-OneTime/10^7,0) -> 0 | I41: =E41+G41+H41 -> 55.825198 | J41: =J40+I41 -> 466.76771 | K41: =F41+G41+H41 -> 51.315656 | L41: =L40+K41 -> 427.98564
... A64: 36 | B64: =IF(A64>=Ramp,ST_Target,ST_Start+(ST_Target-ST_Start)*(A64-1)/MAX(1,Ramp-1)) -> 0.375 | C64: =Routed_Day*365/12 -> 12025446 | D64: =C64*B64 -> 4509542.4 | E64: =C64*(B64*Save_Sold_Base+(1-B64)*Save_Unsold)/10^7 -> 55.885198 | F64: =C64*(B64*Save_Sold_High+(1-B64)*Save_Unsold)/10^7 -> 51.375656 | G64: =-Running_M/10^7 -> -0.06 | H64: =IF(A64=1,-OneTime/10^7,0) -> 0 | I64: =E64+G64+H64 -> 55.825198 | J64: =J63+I64 -> 1750.7473 | K64: =F64+G64+H64 -> 51.315656 | L64: =L63+K64 -> 1608.2457

Sheet Scenarios
A1: Scenarios - what if the assumptions are wrong?
A2: A. Saving per parcel routed into Hypersale (sold and unsold averaged)
A3: Sell-through | B3: ₹35 base | C3: ₹45 high
A4: 0 | B4: =A4*Save_Sold_Base+(1-A4)*Save_Unsold -> -2.2764228 | C4: =A4*Save_Sold_High+(1-A4)*Save_Unsold -> -2.2764228
A5: 0.1 | B5: =A5*Save_Sold_Base+(1-A5)*Save_Unsold -> 10.723277 | C5: =A5*Save_Sold_High+(1-A5)*Save_Unsold -> 9.7232772
A6: 0.2 | B6: =A6*Save_Sold_Base+(1-A6)*Save_Unsold -> 23.722977 | C6: =A6*Save_Sold_High+(1-A6)*Save_Unsold -> 21.722977
A7: 0.3 | B7: =A7*Save_Sold_Base+(1-A7)*Save_Unsold -> 36.722677 | C7: =A7*Save_Sold_High+(1-A7)*Save_Unsold -> 33.722677
A8: 0.375 | B8: =A8*Save_Sold_Base+(1-A8)*Save_Unsold -> 46.472452 | C8: =A8*Save_Sold_High+(1-A8)*Save_Unsold -> 42.722452
A9: 0.5 | B9: =A9*Save_Sold_Base+(1-A9)*Save_Unsold -> 62.722077 | C9: =A9*Save_Sold_High+(1-A9)*Save_Unsold -> 57.722077
A10: 0.75 | B10: =A10*Save_Sold_Base+(1-A10)*Save_Unsold -> 95.221327 | C10: =A10*Save_Sold_High+(1-A10)*Save_Unsold -> 87.721327
A11: 1 | B11: =A11*Save_Sold_Base+(1-A11)*Save_Unsold -> 127.72058 | C11: =A11*Save_Sold_High+(1-A11)*Save_Unsold -> 117.72058
A13: B. Annual net profit, India-wide (steady state)
A14: Sell-through | B14: ₹35 base | C14: ₹45 high | D14: RTO parcels saved / year | E14: Share of RTO saved
A15: 0.1 | B15: =(Routed_Day*365*(A15*Save_Sold_Base+(1-A15)*Save_Unsold)-12*Running_M)/10^7 -> 154.02264 | C15: =(Routed_Day*365*(A15*Save_Sold_High+(1-A15)*Save_Unsold)-12*Running_M)/10^7 -> 139.5921 | D15: =Routed_Day*365*A15/10^5 -> 144.30536 | E15: =Routed_Day*A15/RTO_Day -> 0.055372149
A16: 0.25 | B16: =(Routed_Day*365*(A16*Save_Sold_Base+(1-A16)*Save_Unsold)-12*Running_M)/10^7 -> 435.41159 | C16: =(Routed_Day*365*(A16*Save_Sold_High+(1-A16)*Save_Unsold)-12*Running_M)/10^7 -> 399.33525 | D16: =Routed_Day*365*A16/10^5 -> 360.76339 | E16: =Routed_Day*A16/RTO_Day -> 0.13843037
A17: 0.375 | B17: =(Routed_Day*365*(A17*Save_Sold_Base+(1-A17)*Save_Unsold)-12*Running_M)/10^7 -> 669.90238 | C17: =(Routed_Day*365*(A17*Save_Sold_High+(1-A17)*Save_Unsold)-12*Running_M)/10^7 -> 615.78787 | D17: =Routed_Day*365*A17/10^5 -> 541.14509 | E17: =Routed_Day*A17/RTO_Day -> 0.20764556
A18: 0.5 | B18: =(Routed_Day*365*(A18*Save_Sold_Base+(1-A18)*Save_Unsold)-12*Running_M)/10^7 -> 904.39318 | C18: =(Routed_Day*365*(A18*Save_Sold_High+(1-A18)*Save_Unsold)-12*Running_M)/10^7 -> 832.2405 | D18: =Routed_Day*365*A18/10^5 -> 721.52679 | E18: =Routed_Day*A18/RTO_Day -> 0.27686074
A19: 0.75 | B19: =(Routed_Day*365*(A19*Save_Sold_Base+(1-A19)*Save_Unsold)-12*Running_M)/10^7 -> 1373.3748 | C19: =(Routed_Day*365*(A19*Save_Sold_High+(1-A19)*Save_Unsold)-12*Running_M)/10^7 -> 1265.1457 | D19: =Routed_Day*365*A19/10^5 -> 1082.2902 | E19: =Routed_Day*A19/RTO_Day -> 0.41529112
A21: C. Annual net profit if some buyers are at another hub (Tier B)
A22: Share of sales via Tier B | B22: ₹35 base | C22: ₹45 high | D22: Extra cost per sale (avg)
A23: 0 | B23: =(Routed_Day*365*(ST_Target*(Save_Sold_Base-(A23-TierB_Share)*(TierB_Extra+TierB_Transfer))+(1-ST_Target)*Save_Unsold)-12*Running_M)/10^7 -> 705.07681 | C23: =(Routed_Day*365*(ST_Target*(Save_Sold_High-(A23-TierB_Share)*(TierB_Extra+TierB_Transfer))+(1-ST_Target)*Save_Unsold)-12*Running_M)/10^7 -> 650.9623 | D23: =A23*(TierB_Extra+TierB_Transfer) -> 0
A24: 0.1 | B24: =(Routed_Day*365*(ST_Target*(Save_Sold_Base-(A24-TierB_Share)*(TierB_Extra+TierB_Transfer))+(1-ST_Target)*Save_Unsold)-12*Running_M)/10^7 -> 691.00704 | C24: =(Routed_Day*365*(ST_Target*(Save_Sold_High-(A24-TierB_Share)*(TierB_Extra+TierB_Transfer))+(1-ST_Target)*Save_Unsold)-12*Running_M)/10^7 -> 636.89253 | D24: =A24*(TierB_Extra+TierB_Transfer) -> 2.6
A25: 0.25 | B25: =(Routed_Day*365*(ST_Target*(Save_Sold_Base-(A25-TierB_Share)*(TierB_Extra+TierB_Transfer))+(1-ST_Target)*Save_Unsold)-12*Running_M)/10^7 -> 669.90238 | C25: =(Routed_Day*365*(ST_Target*(Save_Sold_High-(A25-TierB_Share)*(TierB_Extra+TierB_Transfer))+(1-ST_Target)*Save_Unsold)-12*Running_M)/10^7 -> 615.78787 | D25: =A25*(TierB_Extra+TierB_Transfer) -> 6.5
A26: 0.5 | B26: =(Routed_Day*365*(ST_Target*(Save_Sold_Base-(A26-TierB_Share)*(TierB_Extra+TierB_Transfer))+(1-ST_Target)*Save_Unsold)-12*Running_M)/10^7 -> 634.72795 | C26: =(Routed_Day*365*(ST_Target*(Save_Sold_High-(A26-TierB_Share)*(TierB_Extra+TierB_Transfer))+(1-ST_Target)*Save_Unsold)-12*Running_M)/10^7 -> 580.61344 | D26: =A26*(TierB_Extra+TierB_Transfer) -> 13
A27: 0.65 | B27: =(Routed_Day*365*(ST_Target*(Save_Sold_Base-(A27-TierB_Share)*(TierB_Extra+TierB_Transfer))+(1-ST_Target)*Save_Unsold)-12*Running_M)/10^7 -> 613.62329 | C27: =(Routed_Day*365*(ST_Target*(Save_Sold_High-(A27-TierB_Share)*(TierB_Extra+TierB_Transfer))+(1-ST_Target)*Save_Unsold)-12*Running_M)/10^7 -> 559.50878 | D27: =A27*(TierB_Extra+TierB_Transfer) -> 16.9

Sheet Benchmarks
A1: Benchmarks — who else resells failed deliveries locally
A2: Company | B2: What they do | C2: Key number | D2: Lesson for Hypersale | E2: Source
A3: Ozon (Russia) — closest match | B3: Since 10 Sep 2026, refused or uncollected orders stay at the pickup point and are re-listed, if the point has shelf space. Large items, perishables and jewellery excluded. Automatic for sellers. | C3: Pickup-point owners paid 0.20 RUB per litre per day for held stock | D3: Gate eligibility on shelf space; exclude categories; pay the hub for storage | E3: selsup.ru/blog/ozon-prodazha-tovarov-iz-pvz
A4: Zomato Food Rescue (India) | B4: A cancelled order in transit is offered to users within 3 km at a lower price. Prepaid only; the original customer can't rebuy it; 2 cancellations per user per month. | C4: ~4 lakh cancelled orders/month; 75% of eligible orders claimed (Mar 2025) | D4: Anti-gaming rules; prepaid only; let sellers opt out (mandatory rollout drew pushback) | E4: storyboard18.com; greenqueen.com.hk
A5: Wildberries (Russia) | B5: Customers pay a fee for refusing or not collecting an order. | C5: 100 RUB refusal / 200 RUB not collected (Mar 2025); ≤1% of orders | D5: Pairs with Hypersale: the refuser pays part of the wasted trip | E5: oborot.ru
A6: Amazon Grade & Resell (UK/US/EU) | B6: Returned items graded into 4 conditions and re-listed as used at the seller's chosen price. | C6: Live UK 2021, US end-2021, EU 2022 | D6: Add a condition check; full price only for sealed parcels | E6: aboutamazon.co.uk
A7: Amazon FBA Liquidations | B7: Returned or excess stock sold in bulk to resale partners instead of shipping back. | C7: No figures published | D7: Day-8 fallback for unsold items instead of the full reverse trip | E7: aboutamazon.co.uk
A8: Returnless refunds (Amazon, Walmart) | B8: When a return costs more than the item is worth, the item is never collected. | C8: Return processing ~$12–33 (vendor estimate) | D8: At ₹270 AOV a ₹120 RTO is 44% of value — set a price floor for Hypersale | E8: claimlane.com
A9: Jumia (Africa) | B9: Failed deliveries checked in the local warehouse; passing items re-listed, failing items disposed of locally. | C9: No figures published | D9: Local QC gate; local disposal for items that fail it | E9: vendor.jumia.com
A10: Too Good To Go (Europe/US) | B10: Nearby surplus shown on a map, reserved and paid in-app, collected at a set time. | C10: Food at half price or less | D10: UX model for a local, prepaid, time-boxed listing | E10: toogoodtogo.com
A11: Flipkart 2GUD (India) | B11: Marketplace for certified returned and refurbished goods with warranties. | C11: Priced at 50–80% of original | D11: Opened goods needed a discount — keep original price for sealed parcels only | E11: entrackr.com
